// converted by version 1.3
// on Wed Jun 14 15:05:04 EDT 2023

.package test {
	.aid 0xA0:0x40:0x41:0x42:0x43:0x44:0x45:0x46:0x10;
	.version 1.0;

	.imports {
		0xA0:0x0:0x0:0x0:0x62:0x1:0x1 1.2;		//javacard/framework
		0xA0:0x0:0x0:0x0:0x62:0x1:0x2 1.2;		//javacard/security
	}

	.applet {
		0xA0:0x40:0x41:0x42:0x43:0x44:0x45:0x46:0x10:0x1 test;
	}

	.constantPool {
		// 0
		staticMethodRef 0.3.0()V;		// javacard/framework/Applet.<init>()V
		// 1
		virtualMethodRef 0.3.1()V;		// javacard/framework/Applet.register()V
		// 2
		classRef test;
		// 3
		staticMethodRef test/<init>()V;
		// 4
		virtualMethodRef 0.10.1()[B;		// javacard/framework/APDU.getBuffer()[B
		// 5
		virtualMethodRef 0.3.3()Z;		// javacard/framework/Applet.selectingApplet()Z
		// 6
		staticMethodRef test/replyHELLOMSG(Ljavacard/framework/APDU;)V;
			.descriptor	Ljavacard/framework/APDU;	0.10;

		// 7
		virtualMethodRef test/loadKeysAndVerify(Ljavacard/framework/APDU;)V;
			.descriptor	Ljavacard/framework/APDU;	0.10;

		// 8
		staticMethodRef 0.7.1(S)V;		// javacard/framework/ISOException.throwIt(S)V
		// 9
		classRef 1.16;		// javacard/security/KeyPair
		// 10
		staticMethodRef 1.16.0(BS)V;		// javacard/security/KeyPair.<init>(BS)V
		// 11
		virtualMethodRef 1.16.1()V;		// javacard/security/KeyPair.genKeyPair()V
		// 12
		virtualMethodRef 1.16.3()Ljavacard/security/PublicKey;;		// javacard/security/KeyPair.getPublic()Ljavacard/security/PublicKey;
			.descriptor	Ljavacard/security/PublicKey;	1.3;

		// 13
		classRef 1.19;		// javacard/security/ECPublicKey
		// 14
		virtualMethodRef 0.10.8(SS)V;		// javacard/framework/APDU.setOutgoingAndSend(SS)V
		// 15
		virtualMethodRef 0.10.6()S;		// javacard/framework/APDU.setIncomingAndReceive()S
		// 16
		virtualMethodRef 1.16.2()Ljavacard/security/PrivateKey;;		// javacard/security/KeyPair.getPrivate()Ljavacard/security/PrivateKey;
			.descriptor	Ljavacard/security/PrivateKey;	1.2;

		// 17
		classRef 1.18;		// javacard/security/ECPrivateKey
		// 18
		staticMethodRef 1.15.0(BZ)Ljavacard/security/Signature;;		// javacard/security/Signature.getInstance(BZ)Ljavacard/security/Signature;
			.descriptor	Ljavacard/security/Signature;	1.15;

		// 19
		virtualMethodRef 1.15.3(Ljavacard/security/Key;B)V;		// javacard/security/Signature.init(Ljavacard/security/Key;B)V
			.descriptor	Ljavacard/security/Key;	1.0;

		// 20
		virtualMethodRef 1.15.5([BSS[BS)S;		// javacard/security/Signature.sign([BSS[BS)S
		// 21
		virtualMethodRef 1.15.7([BSS[BSS)Z;		// javacard/security/Signature.verify([BSS[BSS)Z
		// 22
		staticMethodRef 1.13.0(BSZ)Ljavacard/security/Key;;		// javacard/security/KeyBuilder.buildKey(BSZ)Ljavacard/security/Key;
			.descriptor	Ljavacard/security/Key;	1.0;

		// 23
		staticFieldRef byte[] test/publickeybytes;
		// 24
		staticFieldRef byte[] test/privatekeybytes;
		// 25
		staticFieldRef byte[] test/signaturebytes;
	}

	.class public test 0 extends 0.3 {		// extends javacard/framework/Applet

		.fields {
			static final byte[] privatekeybytes = {-7,94,73,5,-89,34,-26,-67,-39,28,22,70,73,9,-71,-5,-54,-19,-80,4,-44,-127,-101,58};		// [B
			static final byte[] publickeybytes = {4,-119,-90,20,20,-108,42,-77,82,56,-111,67,34,40,-110,-40,-36,70,22,-47,-43,78,34,89,77,32,-77,-27,-47,-53,-107,35,-82,72,-110,38,44,-41,-78,-127,71,-113,-94,77,1,-128,4,-21,-42};		// [B
			static final byte[] signaturebytes = {48,53,2,24,95,96,-79,14,122,18,26,54,-7,-44,-15,-92,-110,-75,65,-111,62,69,47,53,74,97,23,37,2,25,0,-25,42,121,86,112,9,42,-119,15,123,106,-9,-78,103,-51,14,-102,-108,-41,56,-98,49,99,-113};		// [B
			private static final byte HELLOMSG = 0;		// B
			private static final byte GETMASTER = 5;		// B
		}

		.publicMethodTable 7 {
			equals(Ljava/lang/Object;)Z;
			register()V;
			register([BSB)V;
			selectingApplet()Z;
			deselect()V;
			getShareableInterfaceObject(Ljavacard/framework/AID;B)Ljavacard/framework/Shareable;;
			select()Z;
			process(Ljavacard/framework/APDU;)V;
			loadKeysAndVerify(Ljavacard/framework/APDU;)V;
		}

		.packageMethodTable 0 {
		}

		.implementedInterfaceInfoTable { 
			.interface 0.0 { 		// javacard/framework/ISO7816
			}

		}

		.method protected <init>()V 0 {
			.stack 1;
			.locals 0;

				L0:	aload_0;
					invokespecial 0;		// javacard/framework/Applet.<init>()V
					aload_0;
					invokevirtual 1;		// javacard/framework/Applet.register()V
					return;
		}

		.method public static install([BSB)V 1 {
			.stack 2;
			.locals 0;

				L0:	new 2;		// test/test
					dup;
					invokespecial 3;		// test/test.<init>()V
					pop;
					return;
		}

		.method public process(Ljavacard/framework/APDU;)V 7 {
			.stack 2;
			.locals 3;

			.descriptor	Ljavacard/framework/APDU;	0.10;

				L0:	aload_1;
					invokevirtual 4;		// javacard/framework/APDU.getBuffer()[B
					astore_2;
					aload_2;
					sconst_1;
					baload;
					sstore_3;
					sconst_m1;
					sstore 4;
					aload_0;
					invokevirtual 5;		// javacard/framework/Applet.selectingApplet()Z
					ifeq L2;
				L1:	return;
				L2:	sload_3;
					slookupswitch L5 2 0 L3 5 L4;
				L3:	aload_1;
					invokestatic 6;		// test/test.replyHELLOMSG(Ljavacard/framework/APDU;)V
					goto L6;
				L4:	aload_0;
					aload_1;
					invokevirtual 7;		// test/test.loadKeysAndVerify(Ljavacard/framework/APDU;)V
					goto L6;
				L5:	sspush 137;
					invokestatic 8;		// javacard/framework/ISOException.throwIt(S)V
				L6:	return;
		}

		.method public static replyHELLOMSG(Ljavacard/framework/APDU;)V 2 {
			.stack 4;
			.locals 5;

			.descriptor	Ljavacard/framework/APDU;	0.10;

				L0:	aload_0;
					invokevirtual 4;		// javacard/framework/APDU.getBuffer()[B
					astore_1;
					new 9;		// javacard/security/KeyPair
					dup;
					sconst_5;
					sspush 192;
					invokespecial 10;		// javacard/security/KeyPair.<init>(BS)V
					astore_2;
					aload_2;
					invokevirtual 11;		// javacard/security/KeyPair.genKeyPair()V
					aload_2;
					invokevirtual 12;		// javacard/security/KeyPair.getPublic()Ljavacard/security/PublicKey;
					checkcast 0 13;		// T_CLASSORINTERFACE javacard/security/ECPublicKey
					astore_3;
					aload_3;
					aload_1;
					sconst_5;
					invokeinterface 3 13 19;		// javacard/security/ECPublicKey
					sstore 4;
					sconst_3;
					newarray 11;
					dup;
					sconst_0;
					sconst_5;
					bastore;
					dup;
					sconst_1;
					bspush 6;
					bastore;
					dup;
					sconst_2;
					bspush 87;
					bastore;
					astore 5;
					aload_0;
					sconst_5;
					sload 4;
					invokevirtual 14;		// javacard/framework/APDU.setOutgoingAndSend(SS)V
					return;
		}

		.method public static sendPublicKey(Ljavacard/framework/APDU;)V 3 {
			.stack 4;
			.locals 4;

			.descriptor	Ljavacard/framework/APDU;	0.10;

				L0:	aload_0;
					invokevirtual 4;		// javacard/framework/APDU.getBuffer()[B
					astore_1;
					new 9;		// javacard/security/KeyPair
					dup;
					sconst_5;
					sspush 192;
					invokespecial 10;		// javacard/security/KeyPair.<init>(BS)V
					astore_2;
					aload_2;
					invokevirtual 11;		// javacard/security/KeyPair.genKeyPair()V
					aload_2;
					invokevirtual 12;		// javacard/security/KeyPair.getPublic()Ljavacard/security/PublicKey;
					checkcast 0 13;		// T_CLASSORINTERFACE javacard/security/ECPublicKey
					astore_3;
					aload_3;
					aload_1;
					sconst_5;
					invokeinterface 3 13 19;		// javacard/security/ECPublicKey
					sstore 4;
					aload_0;
					sconst_5;
					sload 4;
					invokevirtual 14;		// javacard/framework/APDU.setOutgoingAndSend(SS)V
					return;
		}

		.method public static receiveMaster(Ljavacard/framework/APDU;)V 4 {
			.stack 7;
			.locals 10;

			.descriptor	Ljavacard/framework/APDU;	0.10;

				L0:	aload_0;
					invokevirtual 4;		// javacard/framework/APDU.getBuffer()[B
					astore_1;
					aload_0;
					invokevirtual 15;		// javacard/framework/APDU.setIncomingAndReceive()S
					sstore_2;
					new 9;		// javacard/security/KeyPair
					dup;
					sconst_5;
					sspush 192;
					invokespecial 10;		// javacard/security/KeyPair.<init>(BS)V
					astore_3;
					aload_3;
					invokevirtual 11;		// javacard/security/KeyPair.genKeyPair()V
					aload_3;
					invokevirtual 12;		// javacard/security/KeyPair.getPublic()Ljavacard/security/PublicKey;
					checkcast 0 13;		// T_CLASSORINTERFACE javacard/security/ECPublicKey
					astore 4;
					aload_3;
					invokevirtual 16;		// javacard/security/KeyPair.getPrivate()Ljavacard/security/PrivateKey;
					checkcast 0 17;		// T_CLASSORINTERFACE javacard/security/ECPrivateKey
					astore 5;
					bspush 17;
					sconst_0;
					invokestatic 18;		// javacard/security/Signature.getInstance(BZ)Ljavacard/security/Signature;
					astore 6;
					aload 6;
					aload 5;
					sconst_1;
					invokevirtual 19;		// javacard/security/Signature.init(Ljavacard/security/Key;B)V
					sconst_1;
					newarray 11;
					dup;
					sconst_0;
					sconst_5;
					bastore;
					astore 7;
					bspush 64;
					newarray 11;
					astore 8;
					aload 6;
					aload 7;
					sconst_0;
					sconst_1;
					aload 8;
					sconst_0;
					invokevirtual 20;		// javacard/security/Signature.sign([BSS[BS)S
					pop;
					bspush 17;
					sconst_0;
					invokestatic 18;		// javacard/security/Signature.getInstance(BZ)Ljavacard/security/Signature;
					astore 9;
					aload 9;
					aload 4;
					sconst_2;
					invokevirtual 19;		// javacard/security/Signature.init(Ljavacard/security/Key;B)V
					aload 9;
					aload 7;
					sconst_0;
					sconst_1;
					aload 8;
					sconst_0;
					bspush 64;
					invokevirtual 21;		// javacard/security/Signature.verify([BSS[BSS)Z
					sstore 10;
					sload 10;
					ifne L2;
				L1:	sspush 27010;
					invokestatic 8;		// javacard/framework/ISOException.throwIt(S)V
				L2:	aload_1;
					sconst_5;
					bspush -112;
					bastore;
					aload_0;
					sconst_5;
					sconst_1;
					invokevirtual 14;		// javacard/framework/APDU.setOutgoingAndSend(SS)V
					return;
		}

		.method public loadKeysAndVerify(Ljavacard/framework/APDU;)V 8 {
			.stack 7;
			.locals 6;

			.descriptor	Ljavacard/framework/APDU;	0.10;

				L0:	bspush 11;
					sspush 192;
					sconst_0;
					invokestatic 22;		// javacard/security/KeyBuilder.buildKey(BSZ)Ljavacard/security/Key;
					checkcast 0 13;		// T_CLASSORINTERFACE javacard/security/ECPublicKey
					astore_2;
					bspush 12;
					sspush 192;
					sconst_0;
					invokestatic 22;		// javacard/security/KeyBuilder.buildKey(BSZ)Ljavacard/security/Key;
					checkcast 0 17;		// T_CLASSORINTERFACE javacard/security/ECPrivateKey
					astore_3;
					aload_2;
					getstatic_a 23;		// reference test/test.publickeybytes
					sconst_0;
					getstatic_a 23;		// reference test/test.publickeybytes
					arraylength;
					invokeinterface 4 13 18;		// javacard/security/ECPublicKey
					aload_3;
					getstatic_a 24;		// reference test/test.privatekeybytes
					sconst_0;
					getstatic_a 24;		// reference test/test.privatekeybytes
					arraylength;
					invokeinterface 4 17 18;		// javacard/security/ECPrivateKey
					bspush 17;
					sconst_0;
					invokestatic 18;		// javacard/security/Signature.getInstance(BZ)Ljavacard/security/Signature;
					astore 4;
					aload 4;
					aload_2;
					sconst_2;
					invokevirtual 19;		// javacard/security/Signature.init(Ljavacard/security/Key;B)V
					sconst_1;
					newarray 11;
					dup;
					sconst_0;
					bspush 83;
					bastore;
					astore 5;
					aload 4;
					aload 5;
					sconst_0;
					aload 5;
					arraylength;
					getstatic_a 25;		// reference test/test.signaturebytes
					sconst_0;
					getstatic_a 25;		// reference test/test.signaturebytes
					arraylength;
					invokevirtual 21;		// javacard/security/Signature.verify([BSS[BSS)Z
					sstore 6;
					aload_1;
					invokevirtual 4;		// javacard/framework/APDU.getBuffer()[B
					astore 7;
					sload 6;
					ifne L2;
				L1:	sspush 27010;
					invokestatic 8;		// javacard/framework/ISOException.throwIt(S)V
				L2:	aload 7;
					sconst_0;
					bspush 32;
					bastore;
					aload 7;
					sconst_1;
					sconst_1;
					bastore;
					aload_1;
					sconst_0;
					sconst_2;
					invokevirtual 14;		// javacard/framework/APDU.setOutgoingAndSend(SS)V
					return;
		}

	}

}
